{
  "db_name": "PostgreSQL",
  "query": "SELECT * from branches WHERE name = $1",
  "describe": {
    "columns": [
      {
        "ordinal": 0,
        "name": "id",
        "type_info": "Int4"
      },
      {
        "ordinal": 1,
        "name": "name",
        "type_info": "Varchar"
      }
    ],
    "parameters": {
      "Left": [
        "Text"
      ]
    },
    "nullable": [
      false,
      false
    ]
  },
  "hash": "4f887194427b0b1bc87d0d875c109a2fd156026b3002585fe6384fc714eda43d"
}
